<?xml version='1.0' encoding='UTF-8'?>
<aas:environment xmlns:aas="https://admin-shell.io/aas/3/0" xmlns:xsi="http://www.w3.org/2001/XMLSchema-instance" xsi:schemaLocation="https://admin-shell.io/aas/3/0 AAS.xsd">
  <aas:assetAdministrationShells>
    <aas:assetAdministrationShell>
      <aas:idShort>defaultAdminShell</aas:idShort>
      <aas:description>
        <aas:langStringTextType>
          <aas:language>en</aas:language>
          <aas:text>defaultAdminShell</aas:text>
        </aas:langStringTextType>
      </aas:description>
      <aas:administration/>
      <aas:id>urn:samm:io.catenax.product_stock:2.0.0#ProductStock</aas:id>
      <aas:assetInformation>
        <aas:assetKind>Type</aas:assetKind>
      </aas:assetInformation>
      <aas:submodels>
        <aas:reference>
          <aas:type>ModelReference</aas:type>
          <aas:keys>
            <aas:key>
              <aas:type>Submodel</aas:type>
              <aas:value>urn:samm:io.catenax.product_stock:2.0.0#ProductStock/submodel</aas:value>
            </aas:key>
          </aas:keys>
        </aas:reference>
      </aas:submodels>
    </aas:assetAdministrationShell>
  </aas:assetAdministrationShells>
  <aas:submodels>
    <aas:submodel>
      <aas:idShort>ProductStock</aas:idShort>
      <aas:description>
        <aas:langStringTextType>
          <aas:language>en</aas:language>
          <aas:text>This aspect represents the latest quantities of a supplier's products that are on stock. The stock represent the build-to-order (BTO) stocks already available for the customer.</aas:text>
        </aas:langStringTextType>
      </aas:description>
      <aas:administration/>
      <aas:id>urn:samm:io.catenax.product_stock:2.0.0#ProductStock/submodel</aas:id>
      <aas:kind>Template</aas:kind>
      <aas:semanticId>
        <aas:type>ModelReference</aas:type>
        <aas:keys>
          <aas:key>
            <aas:type>ConceptDescription</aas:type>
            <aas:value>urn:samm:io.catenax.product_stock:2.0.0#ProductStock</aas:value>
          </aas:key>
        </aas:keys>
      </aas:semanticId>
      <aas:submodelElements>
        <aas:submodelElementList>
          <aas:idShort>positions</aas:idShort>
          <aas:displayName>
            <aas:langStringNameType>
              <aas:language>en</aas:language>
              <aas:text>Positions</aas:text>
            </aas:langStringNameType>
          </aas:displayName>
          <aas:description>
            <aas:langStringTextType>
              <aas:language>en</aas:language>
              <aas:text>The positions refer to positions within an order that refer to the given product (see materialNumberSupplier, materialNumberCustomer and materialNumberDataSpace) for which the stocks are transferred. The positions are differentiated by the orderPositionReference.</aas:text>
            </aas:langStringTextType>
          </aas:description>
          <aas:orderRelevant>true</aas:orderRelevant>
          <aas:typeValueListElement>DataElement</aas:typeValueListElement>
          <aas:value>
            <aas:submodelElementCollection>
              <aas:idShort>Position</aas:idShort>
              <aas:displayName>
                <aas:langStringNameType>
                  <aas:language>en</aas:language>
                  <aas:text>Position</aas:text>
                </aas:langStringNameType>
              </aas:displayName>
              <aas:description>
                <aas:langStringTextType>
                  <aas:language>en</aas:language>
                  <aas:text>The Position can be located at several stocks. A position may be anonymous or may reference an position within an order.</aas:text>
                </aas:langStringTextType>
              </aas:description>
              <aas:value>
                <aas:submodelElementCollection>
                  <aas:idShort>OrderPositionReference</aas:idShort>
                  <aas:displayName>
                    <aas:langStringNameType>
                      <aas:language>en</aas:language>
                      <aas:text>Reference to Order Position</aas:text>
                    </aas:langStringNameType>
                  </aas:displayName>
                  <aas:description>
                    <aas:langStringTextType>
                      <aas:language>en</aas:language>
                      <aas:text>Encapsulates the references to identify a position within an order.</aas:text>
                    </aas:langStringTextType>
                  </aas:description>
                  <aas:value>
                    <aas:property>
                      <aas:idShort>supplierOrderId</aas:idShort>
                      <aas:displayName>
                        <aas:langStringNameType>
                          <aas:language>en</aas:language>
                          <aas:text>Supplier Order ID</aas:text>
                        </aas:langStringNameType>
                      </aas:displayName>
                      <aas:semanticId>
                        <aas:type>ExternalReference</aas:type>
                        <aas:keys>
                          <aas:key>
                            <aas:type>ConceptDescription</aas:type>
                            <aas:value>urn:samm:io.catenax.product_stock:2.0.0#supplierOrderId</aas:value>
                          </aas:key>
                        </aas:keys>
                      </aas:semanticId>
                      <aas:valueType>xs:string</aas:valueType>
                      <aas:value></aas:value>
                    </aas:property>
                    <aas:property>
                      <aas:idShort>customerOrderId</aas:idShort>
                      <aas:displayName>
                        <aas:langStringNameType>
                          <aas:language>en</aas:language>
                          <aas:text>Customer Order ID</aas:text>
                        </aas:langStringNameType>
                      </aas:displayName>
                      <aas:semanticId>
                        <aas:type>ExternalReference</aas:type>
                        <aas:keys>
                          <aas:key>
                            <aas:type>ConceptDescription</aas:type>
                            <aas:value>urn:samm:io.catenax.product_stock:2.0.0#customerOrderId</aas:value>
                          </aas:key>
                        </aas:keys>
                      </aas:semanticId>
                      <aas:valueType>xs:string</aas:valueType>
                      <aas:value></aas:value>
                    </aas:property>
                    <aas:property>
                      <aas:idShort>customerOrderPositionId</aas:idShort>
                      <aas:displayName>
                        <aas:langStringNameType>
                          <aas:language>en</aas:language>
                          <aas:text>Customer Order Position ID</aas:text>
                        </aas:langStringNameType>
                      </aas:displayName>
                      <aas:semanticId>
                        <aas:type>ExternalReference</aas:type>
                        <aas:keys>
                          <aas:key>
                            <aas:type>ConceptDescription</aas:type>
                            <aas:value>urn:samm:io.catenax.product_stock:2.0.0#customerOrderPositionId</aas:value>
                          </aas:key>
                        </aas:keys>
                      </aas:semanticId>
                      <aas:valueType>xs:string</aas:valueType>
                      <aas:value></aas:value>
                    </aas:property>
                  </aas:value>
                </aas:submodelElementCollection>
                <aas:property>
                  <aas:idShort>lastUpdatedOnDateTime</aas:idShort>
                  <aas:displayName>
                    <aas:langStringNameType>
                      <aas:language>en</aas:language>
                      <aas:text>Lasted Updated on Date</aas:text>
                    </aas:langStringNameType>
                  </aas:displayName>
                  <aas:semanticId>
                    <aas:type>ExternalReference</aas:type>
                    <aas:keys>
                      <aas:key>
                        <aas:type>ConceptDescription</aas:type>
                        <aas:value>urn:samm:io.catenax.product_stock:2.0.0#lastUpdatedOnDateTime</aas:value>
                      </aas:key>
                    </aas:keys>
                  </aas:semanticId>
                  <aas:valueType>xs:date</aas:valueType>
                  <aas:value></aas:value>
                </aas:property>
                <aas:submodelElementList>
                  <aas:idShort>allocatedStocks</aas:idShort>
                  <aas:displayName>
                    <aas:langStringNameType>
                      <aas:language>en</aas:language>
                      <aas:text>Allocated Stocks</aas:text>
                    </aas:langStringNameType>
                  </aas:displayName>
                  <aas:description>
                    <aas:langStringTextType>
                      <aas:language>en</aas:language>
                      <aas:text>Stocks already allocated to the customer. There is one AllocatedStock per supplierStockLocation.</aas:text>
                    </aas:langStringTextType>
                  </aas:description>
                  <aas:orderRelevant>true</aas:orderRelevant>
                  <aas:typeValueListElement>DataElement</aas:typeValueListElement>
                  <aas:value>
                    <aas:submodelElementCollection>
                      <aas:idShort>AllocatedStock</aas:idShort>
                      <aas:displayName>
                        <aas:langStringNameType>
                          <aas:language>en</aas:language>
                          <aas:text>Stock Allocated to Customer</aas:text>
                        </aas:langStringNameType>
                      </aas:displayName>
                      <aas:description>
                        <aas:langStringTextType>
                          <aas:language>en</aas:language>
                          <aas:text>This is the quantity of already produced goods at a given location that has not yet been shipped. The allocated stock is the stock available for the customer and may refer to a given position (see OrderPositionReference). Quantities of Materials belonging to this stock are not available for other positions or customers. This stock consists only of the good parts.</aas:text>
                        </aas:langStringTextType>
                      </aas:description>
                      <aas:value>
                        <aas:submodelElementCollection>
                          <aas:idShort>Quantity</aas:idShort>
                          <aas:displayName>
                            <aas:langStringNameType>
                              <aas:language>en</aas:language>
                              <aas:text>Quantity</aas:text>
                            </aas:langStringNameType>
                          </aas:displayName>
                          <aas:description>
                            <aas:langStringTextType>
                              <aas:language>en</aas:language>
                              <aas:text>Comprises the number of objects and the unit of measurement for the respective child objects</aas:text>
                            </aas:langStringTextType>
                          </aas:description>
                          <aas:value>
                            <aas:property>
                              <aas:idShort>quantityNumber</aas:idShort>
                              <aas:displayName>
                                <aas:langStringNameType>
                                  <aas:language>en</aas:language>
                                  <aas:text>Quantity Number</aas:text>
                                </aas:langStringNameType>
                              </aas:displayName>
                              <aas:semanticId>
                                <aas:type>ExternalReference</aas:type>
                                <aas:keys>
                                  <aas:key>
                                    <aas:type>ConceptDescription</aas:type>
                                    <aas:value>urn:samm:io.catenax.product_stock:2.0.0#quantityNumber</aas:value>
                                  </aas:key>
                                </aas:keys>
                              </aas:semanticId>
                              <aas:valueType>xs:double</aas:valueType>
                              <aas:value></aas:value>
                            </aas:property>
                            <aas:property>
                              <aas:idShort>measurementUnit</aas:idShort>
                              <aas:displayName>
                                <aas:langStringNameType>
                                  <aas:language>en</aas:language>
                                  <aas:text>Measurement Unit</aas:text>
                                </aas:langStringNameType>
                              </aas:displayName>
                              <aas:semanticId>
                                <aas:type>ExternalReference</aas:type>
                                <aas:keys>
                                  <aas:key>
                                    <aas:type>ConceptDescription</aas:type>
                                    <aas:value>urn:samm:io.catenax.product_stock:2.0.0#measurementUnit</aas:value>
                                  </aas:key>
                                </aas:keys>
                              </aas:semanticId>
                              <aas:supplementalSemanticIds>
                                <aas:reference>
                                  <aas:type>ExternalReference</aas:type>
                                  <aas:keys>
                                    <aas:key>
                                      <aas:type>GlobalReference</aas:type>
                                      <aas:value>https://github.com/eclipse-esmf/esmf-semantic-aspect-meta-model/blob/main/esmf-semantic-aspect-meta-model/src/main/resources/samm/unit/2.0.0/units.ttl</aas:value>
                                    </aas:key>
                                  </aas:keys>
                                </aas:reference>
                              </aas:supplementalSemanticIds>
                              <aas:valueType>xs:string</aas:valueType>
                              <aas:value></aas:value>
                            </aas:property>
                          </aas:value>
                        </aas:submodelElementCollection>
                        <aas:submodelElementCollection>
                          <aas:idShort>LocationId</aas:idShort>
                          <aas:displayName>
                            <aas:langStringNameType>
                              <aas:language>en</aas:language>
                              <aas:text>Location ID</aas:text>
                            </aas:langStringNameType>
                          </aas:displayName>
                          <aas:description>
                            <aas:langStringTextType>
                              <aas:language>en</aas:language>
                              <aas:text>A location can be described by different kinds of identifiers. Within Catena-X, a location can either be described by a BPNS or BPNA.</aas:text>
                            </aas:langStringTextType>
                          </aas:description>
                          <aas:supplementalSemanticIds>
                            <aas:reference>
                              <aas:type>ExternalReference</aas:type>
                              <aas:keys>
                                <aas:key>
                                  <aas:type>GlobalReference</aas:type>
                                  <aas:value>https://catena-x.net/fileadmin/user_upload/Standard-Bibliothek/Update_PDF_Maerz/5_BPDM/CX_-_0010_BUSINESS_PARTNER_NUMBER_PlatformCapabilityBPDM_v_1.0.1.pdf</aas:value>
                                </aas:key>
                              </aas:keys>
                            </aas:reference>
                          </aas:supplementalSemanticIds>
                          <aas:value>
                            <aas:property>
                              <aas:idShort>locationIdType</aas:idShort>
                              <aas:displayName>
                                <aas:langStringNameType>
                                  <aas:language>en</aas:language>
                                  <aas:text>Type of Location ID</aas:text>
                                </aas:langStringNameType>
                              </aas:displayName>
                              <aas:semanticId>
                                <aas:type>ExternalReference</aas:type>
                                <aas:keys>
                                  <aas:key>
                                    <aas:type>ConceptDescription</aas:type>
                                    <aas:value>urn:samm:io.catenax.product_stock:2.0.0#locationIdType</aas:value>
                                  </aas:key>
                                </aas:keys>
                              </aas:semanticId>
                              <aas:valueType>xs:string</aas:valueType>
                              <aas:value></aas:value>
                            </aas:property>
                            <aas:property>
                              <aas:idShort>locationId</aas:idShort>
                              <aas:displayName>
                                <aas:langStringNameType>
                                  <aas:language>en</aas:language>
                                  <aas:text>Location ID</aas:text>
                                </aas:langStringNameType>
                              </aas:displayName>
                              <aas:semanticId>
                                <aas:type>ExternalReference</aas:type>
                                <aas:keys>
                                  <aas:key>
                                    <aas:type>ConceptDescription</aas:type>
                                    <aas:value>urn:samm:io.catenax.product_stock:2.0.0#locationId</aas:value>
                                  </aas:key>
                                </aas:keys>
                              </aas:semanticId>
                              <aas:valueType>xs:string</aas:valueType>
                              <aas:value></aas:value>
                            </aas:property>
                          </aas:value>
                        </aas:submodelElementCollection>
                      </aas:value>
                    </aas:submodelElementCollection>
                  </aas:value>
                </aas:submodelElementList>
              </aas:value>
            </aas:submodelElementCollection>
          </aas:value>
        </aas:submodelElementList>
        <aas:property>
          <aas:idShort>materialNumberCustomer</aas:idShort>
          <aas:displayName>
            <aas:langStringNameType>
              <aas:language>en</aas:language>
              <aas:text>Customer Material Number</aas:text>
            </aas:langStringNameType>
          </aas:displayName>
          <aas:semanticId>
            <aas:type>ExternalReference</aas:type>
            <aas:keys>
              <aas:key>
                <aas:type>ConceptDescription</aas:type>
                <aas:value>urn:samm:io.catenax.product_stock:2.0.0#materialNumberCustomer</aas:value>
              </aas:key>
            </aas:keys>
          </aas:semanticId>
          <aas:valueType>xs:string</aas:valueType>
          <aas:value></aas:value>
        </aas:property>
        <aas:property>
          <aas:idShort>materialNumberCatenaX</aas:idShort>
          <aas:displayName>
            <aas:langStringNameType>
              <aas:language>en</aas:language>
              <aas:text>Material UUID Used in Catena-X</aas:text>
            </aas:langStringNameType>
          </aas:displayName>
          <aas:semanticId>
            <aas:type>ExternalReference</aas:type>
            <aas:keys>
              <aas:key>
                <aas:type>ConceptDescription</aas:type>
                <aas:value>urn:samm:io.catenax.product_stock:2.0.0#materialNumberCatenaX</aas:value>
              </aas:key>
            </aas:keys>
          </aas:semanticId>
          <aas:valueType>xs:string</aas:valueType>
          <aas:value></aas:value>
        </aas:property>
        <aas:property>
          <aas:idShort>materialNumberSupplier</aas:idShort>
          <aas:displayName>
            <aas:langStringNameType>
              <aas:language>en</aas:language>
              <aas:text>Supplier Material Number</aas:text>
            </aas:langStringNameType>
          </aas:displayName>
          <aas:semanticId>
            <aas:type>ExternalReference</aas:type>
            <aas:keys>
              <aas:key>
                <aas:type>ConceptDescription</aas:type>
                <aas:value>urn:samm:io.catenax.product_stock:2.0.0#materialNumberSupplier</aas:value>
              </aas:key>
            </aas:keys>
          </aas:semanticId>
          <aas:valueType>xs:string</aas:valueType>
          <aas:value></aas:value>
        </aas:property>
      </aas:submodelElements>
    </aas:submodel>
  </aas:submodels>
  <aas:conceptDescriptions>
    <aas:conceptDescription>
      <aas:category>APPLICATION_CLASS</aas:category>
      <aas:idShort>ProductStock</aas:idShort>
      <aas:displayName>
        <aas:langStringNameType>
          <aas:language>en</aas:language>
          <aas:text>Stock of Products of a Supplier</aas:text>
        </aas:langStringNameType>
      </aas:displayName>
      <aas:description>
        <aas:langStringTextType>
          <aas:language>en</aas:language>
          <aas:text>This aspect represents the latest quantities of a supplier's products that are on stock. The stock represent the build-to-order (BTO) stocks already available for the customer.</aas:text>
        </aas:langStringTextType>
      </aas:description>
      <aas:id>urn:samm:io.catenax.product_stock:2.0.0#ProductStock</aas:id>
      <aas:embeddedDataSpecifications>
        <aas:embeddedDataSpecification>
          <aas:dataSpecification>
            <aas:type>ExternalReference</aas:type>
            <aas:keys>
              <aas:key>
                <aas:type>GlobalReference</aas:type>
                <aas:value>https://admin-shell.io/DataSpecificationTemplates/DataSpecificationIec61360/3/0</aas:value>
              </aas:key>
            </aas:keys>
          </aas:dataSpecification>
          <aas:dataSpecificationContent>
            <aas:dataSpecificationIec61360>
              <aas:preferredName>
                <aas:langStringPreferredNameTypeIec61360>
                  <aas:language>en</aas:language>
                  <aas:text>Stock of Products of a Supplier</aas:text>
                </aas:langStringPreferredNameTypeIec61360>
              </aas:preferredName>
              <aas:shortName>
                <aas:langStringShortNameTypeIec61360>
                  <aas:language>en</aas:language>
                  <aas:text>ProductStock</aas:text>
                </aas:langStringShortNameTypeIec61360>
              </aas:shortName>
              <aas:definition>
                <aas:langStringDefinitionTypeIec61360>
                  <aas:language>en</aas:language>
                  <aas:text>This aspect represents the latest quantities of a supplier's products that are on stock. The stock represent the build-to-order (BTO) stocks already available for the customer.</aas:text>
                </aas:langStringDefinitionTypeIec61360>
              </aas:definition>
            </aas:dataSpecificationIec61360>
          </aas:dataSpecificationContent>
        </aas:embeddedDataSpecification>
      </aas:embeddedDataSpecifications>
    </aas:conceptDescription>
    <aas:conceptDescription>
      <aas:idShort>supplierOrderId</aas:idShort>
      <aas:displayName>
        <aas:langStringNameType>
          <aas:language>en</aas:language>
          <aas:text>Supplier Order ID</aas:text>
        </aas:langStringNameType>
      </aas:displayName>
      <aas:id>urn:samm:io.catenax.product_stock:2.0.0#supplierOrderId</aas:id>
      <aas:embeddedDataSpecifications>
        <aas:embeddedDataSpecification>
          <aas:dataSpecification>
            <aas:type>ExternalReference</aas:type>
            <aas:keys>
              <aas:key>
                <aas:type>GlobalReference</aas:type>
                <aas:value>https://admin-shell.io/DataSpecificationTemplates/DataSpecificationIec61360/3/0</aas:value>
              </aas:key>
            </aas:keys>
          </aas:dataSpecification>
          <aas:dataSpecificationContent>
            <aas:dataSpecificationIec61360>
              <aas:preferredName>
                <aas:langStringPreferredNameTypeIec61360>
                  <aas:language>en</aas:language>
                  <aas:text>Supplier Order ID</aas:text>
                </aas:langStringPreferredNameTypeIec61360>
              </aas:preferredName>
              <aas:shortName>
                <aas:langStringShortNameTypeIec61360>
                  <aas:language>en</aas:language>
                  <aas:text>supplierOrderId</aas:text>
                </aas:langStringShortNameTypeIec61360>
              </aas:shortName>
              <aas:dataType>STRING</aas:dataType>
              <aas:definition>
                <aas:langStringDefinitionTypeIec61360>
                  <aas:language>en</aas:language>
                  <aas:text>This is the order number on the supplier side that is given by e.g., the supplier's enterprise resource planning system.</aas:text>
                </aas:langStringDefinitionTypeIec61360>
              </aas:definition>
            </aas:dataSpecificationIec61360>
          </aas:dataSpecificationContent>
        </aas:embeddedDataSpecification>
      </aas:embeddedDataSpecifications>
    </aas:conceptDescription>
    <aas:conceptDescription>
      <aas:idShort>customerOrderId</aas:idShort>
      <aas:displayName>
        <aas:langStringNameType>
          <aas:language>en</aas:language>
          <aas:text>Customer Order ID</aas:text>
        </aas:langStringNameType>
      </aas:displayName>
      <aas:id>urn:samm:io.catenax.product_stock:2.0.0#customerOrderId</aas:id>
      <aas:embeddedDataSpecifications>
        <aas:embeddedDataSpecification>
          <aas:dataSpecification>
            <aas:type>ExternalReference</aas:type>
            <aas:keys>
              <aas:key>
                <aas:type>GlobalReference</aas:type>
                <aas:value>https://admin-shell.io/DataSpecificationTemplates/DataSpecificationIec61360/3/0</aas:value>
              </aas:key>
            </aas:keys>
          </aas:dataSpecification>
          <aas:dataSpecificationContent>
            <aas:dataSpecificationIec61360>
              <aas:preferredName>
                <aas:langStringPreferredNameTypeIec61360>
                  <aas:language>en</aas:language>
                  <aas:text>Customer Order ID</aas:text>
                </aas:langStringPreferredNameTypeIec61360>
              </aas:preferredName>
              <aas:shortName>
                <aas:langStringShortNameTypeIec61360>
                  <aas:language>en</aas:language>
                  <aas:text>customerOrderId</aas:text>
                </aas:langStringShortNameTypeIec61360>
              </aas:shortName>
              <aas:dataType>STRING</aas:dataType>
              <aas:definition>
                <aas:langStringDefinitionTypeIec61360>
                  <aas:language>en</aas:language>
                  <aas:text>This is the order number on the customer side that can be given by e.g., the customer's enterprise resource planning system.</aas:text>
                </aas:langStringDefinitionTypeIec61360>
              </aas:definition>
            </aas:dataSpecificationIec61360>
          </aas:dataSpecificationContent>
        </aas:embeddedDataSpecification>
      </aas:embeddedDataSpecifications>
    </aas:conceptDescription>
    <aas:conceptDescription>
      <aas:idShort>customerOrderPositionId</aas:idShort>
      <aas:displayName>
        <aas:langStringNameType>
          <aas:language>en</aas:language>
          <aas:text>Customer Order Position ID</aas:text>
        </aas:langStringNameType>
      </aas:displayName>
      <aas:id>urn:samm:io.catenax.product_stock:2.0.0#customerOrderPositionId</aas:id>
      <aas:embeddedDataSpecifications>
        <aas:embeddedDataSpecification>
          <aas:dataSpecification>
            <aas:type>ExternalReference</aas:type>
            <aas:keys>
              <aas:key>
                <aas:type>GlobalReference</aas:type>
                <aas:value>https://admin-shell.io/DataSpecificationTemplates/DataSpecificationIec61360/3/0</aas:value>
              </aas:key>
            </aas:keys>
          </aas:dataSpecification>
          <aas:dataSpecificationContent>
            <aas:dataSpecificationIec61360>
              <aas:preferredName>
                <aas:langStringPreferredNameTypeIec61360>
                  <aas:language>en</aas:language>
                  <aas:text>Customer Order Position ID</aas:text>
                </aas:langStringPreferredNameTypeIec61360>
              </aas:preferredName>
              <aas:shortName>
                <aas:langStringShortNameTypeIec61360>
                  <aas:language>en</aas:language>
                  <aas:text>customerOrderPositionId</aas:text>
                </aas:langStringShortNameTypeIec61360>
              </aas:shortName>
              <aas:dataType>STRING</aas:dataType>
              <aas:definition>
                <aas:langStringDefinitionTypeIec61360>
                  <aas:language>en</aas:language>
                  <aas:text>This is an identifier for the position of an order defined by the customer. It's not a technical identifier, such as an UUID. This identifier is used within the business context when talking about the position.</aas:text>
                </aas:langStringDefinitionTypeIec61360>
              </aas:definition>
            </aas:dataSpecificationIec61360>
          </aas:dataSpecificationContent>
        </aas:embeddedDataSpecification>
      </aas:embeddedDataSpecifications>
    </aas:conceptDescription>
    <aas:conceptDescription>
      <aas:idShort>orderPositionReference</aas:idShort>
      <aas:displayName>
        <aas:langStringNameType>
          <aas:language>en</aas:language>
          <aas:text>Order Position Reference</aas:text>
        </aas:langStringNameType>
      </aas:displayName>
      <aas:id>urn:samm:io.catenax.product_stock:2.0.0#orderPositionReference</aas:id>
      <aas:embeddedDataSpecifications>
        <aas:embeddedDataSpecification>
          <aas:dataSpecification>
            <aas:type>ExternalReference</aas:type>
            <aas:keys>
              <aas:key>
                <aas:type>GlobalReference</aas:type>
                <aas:value>https://admin-shell.io/DataSpecificationTemplates/DataSpecificationIec61360/3/0</aas:value>
              </aas:key>
            </aas:keys>
          </aas:dataSpecification>
          <aas:dataSpecificationContent>
            <aas:dataSpecificationIec61360>
              <aas:preferredName>
                <aas:langStringPreferredNameTypeIec61360>
                  <aas:language>en</aas:language>
                  <aas:text>Order Position Reference</aas:text>
                </aas:langStringPreferredNameTypeIec61360>
              </aas:preferredName>
              <aas:shortName>
                <aas:langStringShortNameTypeIec61360>
                  <aas:language>en</aas:language>
                  <aas:text>orderPositionReference</aas:text>
                </aas:langStringShortNameTypeIec61360>
              </aas:shortName>
              <aas:dataType>STRING</aas:dataType>
              <aas:definition>
                <aas:langStringDefinitionTypeIec61360>
                  <aas:language>en</aas:language>
                  <aas:text>The order position reference contains information to identify a position within an order.</aas:text>
                </aas:langStringDefinitionTypeIec61360>
              </aas:definition>
            </aas:dataSpecificationIec61360>
          </aas:dataSpecificationContent>
        </aas:embeddedDataSpecification>
      </aas:embeddedDataSpecifications>
    </aas:conceptDescription>
    <aas:conceptDescription>
      <aas:idShort>lastUpdatedOnDateTime</aas:idShort>
      <aas:displayName>
        <aas:langStringNameType>
          <aas:language>en</aas:language>
          <aas:text>Lasted Updated on Date</aas:text>
        </aas:langStringNameType>
      </aas:displayName>
      <aas:id>urn:samm:io.catenax.product_stock:2.0.0#lastUpdatedOnDateTime</aas:id>
      <aas:embeddedDataSpecifications>
        <aas:embeddedDataSpecification>
          <aas:dataSpecification>
            <aas:type>ExternalReference</aas:type>
            <aas:keys>
              <aas:key>
                <aas:type>GlobalReference</aas:type>
                <aas:value>https://admin-shell.io/DataSpecificationTemplates/DataSpecificationIec61360/3/0</aas:value>
              </aas:key>
            </aas:keys>
          </aas:dataSpecification>
          <aas:dataSpecificationContent>
            <aas:dataSpecificationIec61360>
              <aas:preferredName>
                <aas:langStringPreferredNameTypeIec61360>
                  <aas:language>en</aas:language>
                  <aas:text>Lasted Updated on Date</aas:text>
                </aas:langStringPreferredNameTypeIec61360>
              </aas:preferredName>
              <aas:shortName>
                <aas:langStringShortNameTypeIec61360>
                  <aas:language>en</aas:language>
                  <aas:text>lastUpdatedOnDateTime</aas:text>
                </aas:langStringShortNameTypeIec61360>
              </aas:shortName>
              <aas:dataType>STRING</aas:dataType>
              <aas:definition>
                <aas:langStringDefinitionTypeIec61360>
                  <aas:language>en</aas:language>
                  <aas:text>Date and time at which the position has been updated by the supplier's systems. Date and time are set according to a timezone.</aas:text>
                </aas:langStringDefinitionTypeIec61360>
              </aas:definition>
            </aas:dataSpecificationIec61360>
          </aas:dataSpecificationContent>
        </aas:embeddedDataSpecification>
      </aas:embeddedDataSpecifications>
    </aas:conceptDescription>
    <aas:conceptDescription>
      <aas:idShort>quantityNumber</aas:idShort>
      <aas:displayName>
        <aas:langStringNameType>
          <aas:language>en</aas:language>
          <aas:text>Quantity Number</aas:text>
        </aas:langStringNameType>
      </aas:displayName>
      <aas:id>urn:samm:io.catenax.product_stock:2.0.0#quantityNumber</aas:id>
      <aas:embeddedDataSpecifications>
        <aas:embeddedDataSpecification>
          <aas:dataSpecification>
            <aas:type>ExternalReference</aas:type>
            <aas:keys>
              <aas:key>
                <aas:type>GlobalReference</aas:type>
                <aas:value>https://admin-shell.io/DataSpecificationTemplates/DataSpecificationIec61360/3/0</aas:value>
              </aas:key>
            </aas:keys>
          </aas:dataSpecification>
          <aas:dataSpecificationContent>
            <aas:dataSpecificationIec61360>
              <aas:preferredName>
                <aas:langStringPreferredNameTypeIec61360>
                  <aas:language>en</aas:language>
                  <aas:text>Quantity Number</aas:text>
                </aas:langStringPreferredNameTypeIec61360>
              </aas:preferredName>
              <aas:shortName>
                <aas:langStringShortNameTypeIec61360>
                  <aas:language>en</aas:language>
                  <aas:text>quantityNumber</aas:text>
                </aas:langStringShortNameTypeIec61360>
              </aas:shortName>
              <aas:dataType>REAL_MEASURE</aas:dataType>
              <aas:definition>
                <aas:langStringDefinitionTypeIec61360>
                  <aas:language>en</aas:language>
                  <aas:text>The number of objects related to the measurement unit</aas:text>
                </aas:langStringDefinitionTypeIec61360>
              </aas:definition>
            </aas:dataSpecificationIec61360>
          </aas:dataSpecificationContent>
        </aas:embeddedDataSpecification>
      </aas:embeddedDataSpecifications>
    </aas:conceptDescription>
    <aas:conceptDescription>
      <aas:idShort>measurementUnit</aas:idShort>
      <aas:displayName>
        <aas:langStringNameType>
          <aas:language>en</aas:language>
          <aas:text>Measurement Unit</aas:text>
        </aas:langStringNameType>
      </aas:displayName>
      <aas:id>urn:samm:io.catenax.product_stock:2.0.0#measurementUnit</aas:id>
      <aas:embeddedDataSpecifications>
        <aas:embeddedDataSpecification>
          <aas:dataSpecification>
            <aas:type>ExternalReference</aas:type>
            <aas:keys>
              <aas:key>
                <aas:type>GlobalReference</aas:type>
                <aas:value>https://admin-shell.io/DataSpecificationTemplates/DataSpecificationIec61360/3/0</aas:value>
              </aas:key>
            </aas:keys>
          </aas:dataSpecification>
          <aas:dataSpecificationContent>
            <aas:dataSpecificationIec61360>
              <aas:preferredName>
                <aas:langStringPreferredNameTypeIec61360>
                  <aas:language>en</aas:language>
                  <aas:text>Measurement Unit</aas:text>
                </aas:langStringPreferredNameTypeIec61360>
              </aas:preferredName>
              <aas:shortName>
                <aas:langStringShortNameTypeIec61360>
                  <aas:language>en</aas:language>
                  <aas:text>measurementUnit</aas:text>
                </aas:langStringShortNameTypeIec61360>
              </aas:shortName>
              <aas:dataType>STRING</aas:dataType>
              <aas:definition>
                <aas:langStringDefinitionTypeIec61360>
                  <aas:language>en</aas:language>
                  <aas:text>Unit of measurement for the quantity of objects.
If possible, use units from the aspect meta model unit catalog, which is based on the UNECE Recommendation No. 20 "Codes for Units of Measure used in International Trade".</aas:text>
                </aas:langStringDefinitionTypeIec61360>
              </aas:definition>
            </aas:dataSpecificationIec61360>
          </aas:dataSpecificationContent>
        </aas:embeddedDataSpecification>
      </aas:embeddedDataSpecifications>
    </aas:conceptDescription>
    <aas:conceptDescription>
      <aas:idShort>quantityOnAllocatedStock</aas:idShort>
      <aas:displayName>
        <aas:langStringNameType>
          <aas:language>en</aas:language>
          <aas:text>Quantity on Allocated Stock</aas:text>
        </aas:langStringNameType>
      </aas:displayName>
      <aas:id>urn:samm:io.catenax.product_stock:2.0.0#quantityOnAllocatedStock</aas:id>
      <aas:embeddedDataSpecifications>
        <aas:embeddedDataSpecification>
          <aas:dataSpecification>
            <aas:type>ExternalReference</aas:type>
            <aas:keys>
              <aas:key>
                <aas:type>GlobalReference</aas:type>
                <aas:value>https://admin-shell.io/DataSpecificationTemplates/DataSpecificationIec61360/3/0</aas:value>
              </aas:key>
            </aas:keys>
          </aas:dataSpecification>
          <aas:dataSpecificationContent>
            <aas:dataSpecificationIec61360>
              <aas:preferredName>
                <aas:langStringPreferredNameTypeIec61360>
                  <aas:language>en</aas:language>
                  <aas:text>Quantity on Allocated Stock</aas:text>
                </aas:langStringPreferredNameTypeIec61360>
              </aas:preferredName>
              <aas:shortName>
                <aas:langStringShortNameTypeIec61360>
                  <aas:language>en</aas:language>
                  <aas:text>quantityOnAllocatedStock</aas:text>
                </aas:langStringShortNameTypeIec61360>
              </aas:shortName>
              <aas:dataType>STRING</aas:dataType>
              <aas:definition>
                <aas:langStringDefinitionTypeIec61360>
                  <aas:language>en</aas:language>
                  <aas:text>This is the quantity of the material within the position that is already ready to be delivered.</aas:text>
                </aas:langStringDefinitionTypeIec61360>
              </aas:definition>
            </aas:dataSpecificationIec61360>
          </aas:dataSpecificationContent>
        </aas:embeddedDataSpecification>
      </aas:embeddedDataSpecifications>
    </aas:conceptDescription>
    <aas:conceptDescription>
      <aas:idShort>locationIdType</aas:idShort>
      <aas:displayName>
        <aas:langStringNameType>
          <aas:language>en</aas:language>
          <aas:text>Type of Location ID</aas:text>
        </aas:langStringNameType>
      </aas:displayName>
      <aas:id>urn:samm:io.catenax.product_stock:2.0.0#locationIdType</aas:id>
      <aas:embeddedDataSpecifications>
        <aas:embeddedDataSpecification>
          <aas:dataSpecification>
            <aas:type>ExternalReference</aas:type>
            <aas:keys>
              <aas:key>
                <aas:type>GlobalReference</aas:type>
                <aas:value>https://admin-shell.io/DataSpecificationTemplates/DataSpecificationIec61360/3/0</aas:value>
              </aas:key>
            </aas:keys>
          </aas:dataSpecification>
          <aas:dataSpecificationContent>
            <aas:dataSpecificationIec61360>
              <aas:preferredName>
                <aas:langStringPreferredNameTypeIec61360>
                  <aas:language>en</aas:language>
                  <aas:text>Type of Location ID</aas:text>
                </aas:langStringPreferredNameTypeIec61360>
              </aas:preferredName>
              <aas:shortName>
                <aas:langStringShortNameTypeIec61360>
                  <aas:language>en</aas:language>
                  <aas:text>locationIdType</aas:text>
                </aas:langStringShortNameTypeIec61360>
              </aas:shortName>
              <aas:dataType>STRING</aas:dataType>
              <aas:definition>
                <aas:langStringDefinitionTypeIec61360>
                  <aas:language>en</aas:language>
                  <aas:text>Type of the location's ID.</aas:text>
                </aas:langStringDefinitionTypeIec61360>
              </aas:definition>
              <aas:valueList>
                <aas:valueReferencePairs>
                  <aas:valueReferencePair>
                    <aas:value>BPNS</aas:value>
                    <aas:valueId>
                      <aas:type>ModelReference</aas:type>
                      <aas:keys>
                        <aas:key>
                          <aas:type>DataElement</aas:type>
                          <aas:value>urn:samm:io.catenax.product_stock:2.0.0#LocationIdTypeEnum:BPNS</aas:value>
                        </aas:key>
                      </aas:keys>
                    </aas:valueId>
                  </aas:valueReferencePair>
                  <aas:valueReferencePair>
                    <aas:value>BPNA</aas:value>
                    <aas:valueId>
                      <aas:type>ModelReference</aas:type>
                      <aas:keys>
                        <aas:key>
                          <aas:type>DataElement</aas:type>
                          <aas:value>urn:samm:io.catenax.product_stock:2.0.0#LocationIdTypeEnum:BPNA</aas:value>
                        </aas:key>
                      </aas:keys>
                    </aas:valueId>
                  </aas:valueReferencePair>
                </aas:valueReferencePairs>
              </aas:valueList>
            </aas:dataSpecificationIec61360>
          </aas:dataSpecificationContent>
        </aas:embeddedDataSpecification>
      </aas:embeddedDataSpecifications>
    </aas:conceptDescription>
    <aas:conceptDescription>
      <aas:idShort>locationId</aas:idShort>
      <aas:displayName>
        <aas:langStringNameType>
          <aas:language>en</aas:language>
          <aas:text>Location ID</aas:text>
        </aas:langStringNameType>
      </aas:displayName>
      <aas:id>urn:samm:io.catenax.product_stock:2.0.0#locationId</aas:id>
      <aas:embeddedDataSpecifications>
        <aas:embeddedDataSpecification>
          <aas:dataSpecification>
            <aas:type>ExternalReference</aas:type>
            <aas:keys>
              <aas:key>
                <aas:type>GlobalReference</aas:type>
                <aas:value>https://admin-shell.io/DataSpecificationTemplates/DataSpecificationIec61360/3/0</aas:value>
              </aas:key>
            </aas:keys>
          </aas:dataSpecification>
          <aas:dataSpecificationContent>
            <aas:dataSpecificationIec61360>
              <aas:preferredName>
                <aas:langStringPreferredNameTypeIec61360>
                  <aas:language>en</aas:language>
                  <aas:text>Location ID</aas:text>
                </aas:langStringPreferredNameTypeIec61360>
              </aas:preferredName>
              <aas:shortName>
                <aas:langStringShortNameTypeIec61360>
                  <aas:language>en</aas:language>
                  <aas:text>locationId</aas:text>
                </aas:langStringShortNameTypeIec61360>
              </aas:shortName>
              <aas:dataType>STRING</aas:dataType>
              <aas:definition>
                <aas:langStringDefinitionTypeIec61360>
                  <aas:language>en</aas:language>
                  <aas:text>The actual ID reflecting the type (locationIdType) of the location.</aas:text>
                </aas:langStringDefinitionTypeIec61360>
              </aas:definition>
            </aas:dataSpecificationIec61360>
          </aas:dataSpecificationContent>
        </aas:embeddedDataSpecification>
      </aas:embeddedDataSpecifications>
    </aas:conceptDescription>
    <aas:conceptDescription>
      <aas:idShort>supplierStockLocationId</aas:idShort>
      <aas:displayName>
        <aas:langStringNameType>
          <aas:language>en</aas:language>
          <aas:text>Location ID of Supplier's Stock</aas:text>
        </aas:langStringNameType>
      </aas:displayName>
      <aas:id>urn:samm:io.catenax.product_stock:2.0.0#supplierStockLocationId</aas:id>
      <aas:embeddedDataSpecifications>
        <aas:embeddedDataSpecification>
          <aas:dataSpecification>
            <aas:type>ExternalReference</aas:type>
            <aas:keys>
              <aas:key>
                <aas:type>GlobalReference</aas:type>
                <aas:value>https://admin-shell.io/DataSpecificationTemplates/DataSpecificationIec61360/3/0</aas:value>
              </aas:key>
            </aas:keys>
          </aas:dataSpecification>
          <aas:dataSpecificationContent>
            <aas:dataSpecificationIec61360>
              <aas:preferredName>
                <aas:langStringPreferredNameTypeIec61360>
                  <aas:language>en</aas:language>
                  <aas:text>Location ID of Supplier's Stock</aas:text>
                </aas:langStringPreferredNameTypeIec61360>
              </aas:preferredName>
              <aas:shortName>
                <aas:langStringShortNameTypeIec61360>
                  <aas:language>en</aas:language>
                  <aas:text>supplierStockLocationId</aas:text>
                </aas:langStringShortNameTypeIec61360>
              </aas:shortName>
              <aas:dataType>STRING</aas:dataType>
              <aas:definition>
                <aas:langStringDefinitionTypeIec61360>
                  <aas:language>en</aas:language>
                  <aas:text>One stock has always one location. The location is identified using BPNs. The location can be identified differently depending on the partner.</aas:text>
                </aas:langStringDefinitionTypeIec61360>
              </aas:definition>
            </aas:dataSpecificationIec61360>
          </aas:dataSpecificationContent>
        </aas:embeddedDataSpecification>
      </aas:embeddedDataSpecifications>
    </aas:conceptDescription>
    <aas:conceptDescription>
      <aas:idShort>allocatedStocks</aas:idShort>
      <aas:displayName>
        <aas:langStringNameType>
          <aas:language>en</aas:language>
          <aas:text>Allocated Stocks</aas:text>
        </aas:langStringNameType>
      </aas:displayName>
      <aas:id>urn:samm:io.catenax.product_stock:2.0.0#allocatedStocks</aas:id>
      <aas:embeddedDataSpecifications>
        <aas:embeddedDataSpecification>
          <aas:dataSpecification>
            <aas:type>ExternalReference</aas:type>
            <aas:keys>
              <aas:key>
                <aas:type>GlobalReference</aas:type>
                <aas:value>https://admin-shell.io/DataSpecificationTemplates/DataSpecificationIec61360/3/0</aas:value>
              </aas:key>
            </aas:keys>
          </aas:dataSpecification>
          <aas:dataSpecificationContent>
            <aas:dataSpecificationIec61360>
              <aas:preferredName>
                <aas:langStringPreferredNameTypeIec61360>
                  <aas:language>en</aas:language>
                  <aas:text>Allocated Stocks</aas:text>
                </aas:langStringPreferredNameTypeIec61360>
              </aas:preferredName>
              <aas:shortName>
                <aas:langStringShortNameTypeIec61360>
                  <aas:language>en</aas:language>
                  <aas:text>allocatedStocks</aas:text>
                </aas:langStringShortNameTypeIec61360>
              </aas:shortName>
              <aas:dataType>STRING</aas:dataType>
              <aas:definition>
                <aas:langStringDefinitionTypeIec61360>
                  <aas:language>en</aas:language>
                  <aas:text>Stocks already allocated to the customer. There is one AllocatedStock per supplierStockLocation.</aas:text>
                </aas:langStringDefinitionTypeIec61360>
              </aas:definition>
            </aas:dataSpecificationIec61360>
          </aas:dataSpecificationContent>
        </aas:embeddedDataSpecification>
      </aas:embeddedDataSpecifications>
    </aas:conceptDescription>
    <aas:conceptDescription>
      <aas:idShort>positions</aas:idShort>
      <aas:displayName>
        <aas:langStringNameType>
          <aas:language>en</aas:language>
          <aas:text>Positions</aas:text>
        </aas:langStringNameType>
      </aas:displayName>
      <aas:id>urn:samm:io.catenax.product_stock:2.0.0#positions</aas:id>
      <aas:embeddedDataSpecifications>
        <aas:embeddedDataSpecification>
          <aas:dataSpecification>
            <aas:type>ExternalReference</aas:type>
            <aas:keys>
              <aas:key>
                <aas:type>GlobalReference</aas:type>
                <aas:value>https://admin-shell.io/DataSpecificationTemplates/DataSpecificationIec61360/3/0</aas:value>
              </aas:key>
            </aas:keys>
          </aas:dataSpecification>
          <aas:dataSpecificationContent>
            <aas:dataSpecificationIec61360>
              <aas:preferredName>
                <aas:langStringPreferredNameTypeIec61360>
                  <aas:language>en</aas:language>
                  <aas:text>Positions</aas:text>
                </aas:langStringPreferredNameTypeIec61360>
              </aas:preferredName>
              <aas:shortName>
                <aas:langStringShortNameTypeIec61360>
                  <aas:language>en</aas:language>
                  <aas:text>positions</aas:text>
                </aas:langStringShortNameTypeIec61360>
              </aas:shortName>
              <aas:dataType>STRING</aas:dataType>
              <aas:definition>
                <aas:langStringDefinitionTypeIec61360>
                  <aas:language>en</aas:language>
                  <aas:text>The positions refer to positions within an order that refer to the given product (see materialNumberSupplier, materialNumberCustomer and materialNumberDataSpace) for which the stocks are transferred. The positions are differentiated by the orderPositionReference.</aas:text>
                </aas:langStringDefinitionTypeIec61360>
              </aas:definition>
            </aas:dataSpecificationIec61360>
          </aas:dataSpecificationContent>
        </aas:embeddedDataSpecification>
      </aas:embeddedDataSpecifications>
    </aas:conceptDescription>
    <aas:conceptDescription>
      <aas:idShort>materialNumberCustomer</aas:idShort>
      <aas:displayName>
        <aas:langStringNameType>
          <aas:language>en</aas:language>
          <aas:text>Customer Material Number</aas:text>
        </aas:langStringNameType>
      </aas:displayName>
      <aas:id>urn:samm:io.catenax.product_stock:2.0.0#materialNumberCustomer</aas:id>
      <aas:embeddedDataSpecifications>
        <aas:embeddedDataSpecification>
          <aas:dataSpecification>
            <aas:type>ExternalReference</aas:type>
            <aas:keys>
              <aas:key>
                <aas:type>GlobalReference</aas:type>
                <aas:value>https://admin-shell.io/DataSpecificationTemplates/DataSpecificationIec61360/3/0</aas:value>
              </aas:key>
            </aas:keys>
          </aas:dataSpecification>
          <aas:dataSpecificationContent>
            <aas:dataSpecificationIec61360>
              <aas:preferredName>
                <aas:langStringPreferredNameTypeIec61360>
                  <aas:language>en</aas:language>
                  <aas:text>Customer Material Number</aas:text>
                </aas:langStringPreferredNameTypeIec61360>
              </aas:preferredName>
              <aas:shortName>
                <aas:langStringShortNameTypeIec61360>
                  <aas:language>en</aas:language>
                  <aas:text>materialNumberCustomer</aas:text>
                </aas:langStringShortNameTypeIec61360>
              </aas:shortName>
              <aas:dataType>STRING</aas:dataType>
              <aas:definition>
                <aas:langStringDefinitionTypeIec61360>
                  <aas:language>en</aas:language>
                  <aas:text>Material identifier as assigned by customer. This material number identifies the material (as planned) in customer's database. For standard parts (e.g. screws) for which a customer does not have an own number, the materialNumberSupplier should be set in this field, too.</aas:text>
                </aas:langStringDefinitionTypeIec61360>
              </aas:definition>
            </aas:dataSpecificationIec61360>
          </aas:dataSpecificationContent>
        </aas:embeddedDataSpecification>
      </aas:embeddedDataSpecifications>
    </aas:conceptDescription>
    <aas:conceptDescription>
      <aas:idShort>materialNumberCatenaX</aas:idShort>
      <aas:displayName>
        <aas:langStringNameType>
          <aas:language>en</aas:language>
          <aas:text>Material UUID Used in Catena-X</aas:text>
        </aas:langStringNameType>
      </aas:displayName>
      <aas:id>urn:samm:io.catenax.product_stock:2.0.0#materialNumberCatenaX</aas:id>
      <aas:embeddedDataSpecifications>
        <aas:embeddedDataSpecification>
          <aas:dataSpecification>
            <aas:type>ExternalReference</aas:type>
            <aas:keys>
              <aas:key>
                <aas:type>GlobalReference</aas:type>
                <aas:value>https://admin-shell.io/DataSpecificationTemplates/DataSpecificationIec61360/3/0</aas:value>
              </aas:key>
            </aas:keys>
          </aas:dataSpecification>
          <aas:dataSpecificationContent>
            <aas:dataSpecificationIec61360>
              <aas:preferredName>
                <aas:langStringPreferredNameTypeIec61360>
                  <aas:language>en</aas:language>
                  <aas:text>Material UUID Used in Catena-X</aas:text>
                </aas:langStringPreferredNameTypeIec61360>
              </aas:preferredName>
              <aas:shortName>
                <aas:langStringShortNameTypeIec61360>
                  <aas:language>en</aas:language>
                  <aas:text>materialNumberCatenaX</aas:text>
                </aas:langStringShortNameTypeIec61360>
              </aas:shortName>
              <aas:dataType>STRING</aas:dataType>
              <aas:definition>
                <aas:langStringDefinitionTypeIec61360>
                  <aas:language>en</aas:language>
                  <aas:text>Material identifier used uniquely within Catena-X to identify the Material (e.g. PartAsPlanned).</aas:text>
                </aas:langStringDefinitionTypeIec61360>
              </aas:definition>
            </aas:dataSpecificationIec61360>
          </aas:dataSpecificationContent>
        </aas:embeddedDataSpecification>
      </aas:embeddedDataSpecifications>
    </aas:conceptDescription>
    <aas:conceptDescription>
      <aas:idShort>materialNumberSupplier</aas:idShort>
      <aas:displayName>
        <aas:langStringNameType>
          <aas:language>en</aas:language>
          <aas:text>Supplier Material Number</aas:text>
        </aas:langStringNameType>
      </aas:displayName>
      <aas:id>urn:samm:io.catenax.product_stock:2.0.0#materialNumberSupplier</aas:id>
      <aas:embeddedDataSpecifications>
        <aas:embeddedDataSpecification>
          <aas:dataSpecification>
            <aas:type>ExternalReference</aas:type>
            <aas:keys>
              <aas:key>
                <aas:type>GlobalReference</aas:type>
                <aas:value>https://admin-shell.io/DataSpecificationTemplates/DataSpecificationIec61360/3/0</aas:value>
              </aas:key>
            </aas:keys>
          </aas:dataSpecification>
          <aas:dataSpecificationContent>
            <aas:dataSpecificationIec61360>
              <aas:preferredName>
                <aas:langStringPreferredNameTypeIec61360>
                  <aas:language>en</aas:language>
                  <aas:text>Supplier Material Number</aas:text>
                </aas:langStringPreferredNameTypeIec61360>
              </aas:preferredName>
              <aas:shortName>
                <aas:langStringShortNameTypeIec61360>
                  <aas:language>en</aas:language>
                  <aas:text>materialNumberSupplier</aas:text>
                </aas:langStringShortNameTypeIec61360>
              </aas:shortName>
              <aas:dataType>STRING</aas:dataType>
              <aas:definition>
                <aas:langStringDefinitionTypeIec61360>
                  <aas:language>en</aas:language>
                  <aas:text>Material identifier as assigned by supplier. This material number identifies the material (as planned) in supplier's database.</aas:text>
                </aas:langStringDefinitionTypeIec61360>
              </aas:definition>
            </aas:dataSpecificationIec61360>
          </aas:dataSpecificationContent>
        </aas:embeddedDataSpecification>
      </aas:embeddedDataSpecifications>
    </aas:conceptDescription>
  </aas:conceptDescriptions>
</aas:environment>
