{
  "sensorRuntimeData" : [ {
    "sensorData" : [ {
      "sensorValue" : 32.00,
      "sensorUnit" : "unit:Celsius",
      "sensorType" : "Temperature"
    } ],
    "sensorGeoLocation" : {
      "altitude" : 280.20,
      "geoDataTimestamp" : "2023-02-04T14:48:54",
      "latitude" : 40.20361,
      "longitude" : 11.3102
    },
    "batteryLevel" : 50.00,
    "timestamp" : "2023-02-04T14:48:54",
    "transmissionMethod" : "LoRaWAN"
  } ],
  "catenaXId" : "urn:uuid:ed85f17e-29dd-473c-9cb8-d7ad1dc44d2f"
}