{
  "incoterms" : "DAP (Delivered at Place)",
  "image" : {
    "name" : "eOMtThyhVNLWUZNRcBaQKxI",
    "location" : "telnet://192.0.2.16:80/"
  },
  "catenaXId" : "580d3adf-1981-44a0-a214-13d6ceed9379",
  "quantity" : 50.0,
  "mechanicalDamage" : true,
  "unitOfMeasure" : "each",
  "bundleOffer" : true,
  "availabilityDate" : "2022-03-11",
  "corroded" : true,
  "pickupLocation" : {
    "longitude" : -117.28333,
    "latitude" : 48.137154
  },
  "burned" : true,
  "condition" : "New",
  "attachment" : [ {
    "name" : "yedUsFwdkelQbxeTeQOvaScfqIOOmaa",
    "location" : "ftp://ftp.is.co.za/rfc/rfc1808.txt"
  } ],
  "discolored" : true,
  "price" : {
    "value" : 250.0,
    "currency" : "EUR"
  },
  "missingParts" : true,
  "dismantled" : true,
  "marketplaceProduct" : {
    "manufacturerPartNumber" : "4S7R7002DB",
    "technicalSpecification" : [ {
      "key" : "JxkyvRnL",
      "technicalValue" : "RYtGKbgicZaHCBRQDSx"
    } ],
    "productLink" : "http://www.ietf.org/rfc/rfc2396.txt",
    "oeNumber" : "4B0905851C",
    "category" : {
      "mainCategory" : [ "Audio, video, navigation" ],
      "subCategory" : [ "Amplifiers, subwoofers, etc" ]
    },
    "originalManufacturer" : "BMW",
    "brand" : "ZF",
    "productDescription" : "BMW 3er (E36) BJ: 1996"
  },
  "sku" : "1002090, xYz.09, ABcXYZ",
  "mileage" : 120000.06
}